{
"meta":{"test_sets":[],"test_metrics":[],"learn_metrics":[{"best_value":"Min","name":"RMSE"}],"launch_mode":"Train","parameters":"","iteration_count":100,"learn_sets":["learn"],"name":"experiment"},
"iterations":[
{"learn":[14.005006],"iteration":0,"passed_time":0.00173044285,"remaining_time":0.1713138421},
{"learn":[13.14441192],"iteration":1,"passed_time":0.003516501647,"remaining_time":0.1723085807},
{"learn":[12.34258257],"iteration":2,"passed_time":0.005473058659,"remaining_time":0.17696223},
{"learn":[11.64527793],"iteration":3,"passed_time":0.006646063456,"remaining_time":0.1595055229},
{"learn":[11.02766183],"iteration":4,"passed_time":0.008240609587,"remaining_time":0.1565715822},
{"learn":[10.43485794],"iteration":5,"passed_time":0.009692857623,"remaining_time":0.1518547694},
{"learn":[9.890641275],"iteration":6,"passed_time":0.01145535872,"remaining_time":0.152192623},
{"learn":[9.492161212],"iteration":7,"passed_time":0.01310611201,"remaining_time":0.1507202881},
{"learn":[9.105082953],"iteration":8,"passed_time":0.01463851724,"remaining_time":0.1480116743},
{"learn":[8.674157135],"iteration":9,"passed_time":0.01623970224,"remaining_time":0.1461573202},
{"learn":[8.341743544],"iteration":10,"passed_time":0.01802409862,"remaining_time":0.1458313434},
{"learn":[8.049372916],"iteration":11,"passed_time":0.02002238873,"remaining_time":0.1468308507},
{"learn":[7.757318612],"iteration":12,"passed_time":0.02207292014,"remaining_time":0.1477187733},
{"learn":[7.522206899],"iteration":13,"passed_time":0.02369228904,"remaining_time":0.1455383469},
{"learn":[7.297756655],"iteration":14,"passed_time":0.02542011372,"remaining_time":0.1440473111},
{"learn":[7.088359431],"iteration":15,"passed_time":0.02685507143,"remaining_time":0.140989125},
{"learn":[6.882113791],"iteration":16,"passed_time":0.02832452445,"remaining_time":0.1382903253},
{"learn":[6.704728832],"iteration":17,"passed_time":0.03001571373,"remaining_time":0.1367382514},
{"learn":[6.563881962],"iteration":18,"passed_time":0.03184597319,"remaining_time":0.135764412},
{"learn":[6.418790279],"iteration":19,"passed_time":0.0336271239,"remaining_time":0.1345084956},
{"learn":[6.315756953],"iteration":20,"passed_time":0.03587409113,"remaining_time":0.1349549142},
{"learn":[6.210157751],"iteration":21,"passed_time":0.0379292217,"remaining_time":0.1344763315},
{"learn":[6.115058449],"iteration":22,"passed_time":0.03976309872,"remaining_time":0.1331199392},
{"learn":[6.014819884],"iteration":23,"passed_time":0.04141728149,"remaining_time":0.1311547247},
{"learn":[5.93117229],"iteration":24,"passed_time":0.04298604873,"remaining_time":0.1289581462},
{"learn":[5.844857622],"iteration":25,"passed_time":0.04451024227,"remaining_time":0.1266829972},
{"learn":[5.771145213],"iteration":26,"passed_time":0.04606008302,"remaining_time":0.1245328171},
{"learn":[5.704018229],"iteration":27,"passed_time":0.04761211562,"remaining_time":0.1224311545},
{"learn":[5.665806474],"iteration":28,"passed_time":0.04929995535,"remaining_time":0.1206998907},
{"learn":[5.616500369],"iteration":29,"passed_time":0.05133369497,"remaining_time":0.1197786216},
{"learn":[5.558023666],"iteration":30,"passed_time":0.05298425788,"remaining_time":0.117932703},
{"learn":[5.510080976],"iteration":31,"passed_time":0.05471455592,"remaining_time":0.1162684313},
{"learn":[5.468747792],"iteration":32,"passed_time":0.0563043712,"remaining_time":0.1143149355},
{"learn":[5.429275534],"iteration":33,"passed_time":0.05821897655,"remaining_time":0.1130133074},
{"learn":[5.402117324],"iteration":34,"passed_time":0.05995102042,"remaining_time":0.1113376093},
{"learn":[5.367635151],"iteration":35,"passed_time":0.06151427328,"remaining_time":0.1093587081},
{"learn":[5.345181232],"iteration":36,"passed_time":0.0630884653,"remaining_time":0.1074209004},
{"learn":[5.319151269],"iteration":37,"passed_time":0.06485460055,"remaining_time":0.1058154009},
{"learn":[5.296134146],"iteration":38,"passed_time":0.06672477276,"remaining_time":0.1043643882},
{"learn":[5.269629003],"iteration":39,"passed_time":0.06833525301,"remaining_time":0.1025028795},
{"learn":[5.251147059],"iteration":40,"passed_time":0.06994270423,"remaining_time":0.1006492573},
{"learn":[5.248003302],"iteration":41,"passed_time":0.07061726003,"remaining_time":0.09751907338},
{"learn":[5.232376509],"iteration":42,"passed_time":0.07214530822,"remaining_time":0.09563447834},
{"learn":[5.213524255],"iteration":43,"passed_time":0.0735059301,"remaining_time":0.09355300195},
{"learn":[5.189691584],"iteration":44,"passed_time":0.07496234635,"remaining_time":0.09162064554},
{"learn":[5.166052198],"iteration":45,"passed_time":0.07676157784,"remaining_time":0.09011141747},
{"learn":[5.140406659],"iteration":46,"passed_time":0.07854785907,"remaining_time":0.08857524533},
{"learn":[5.118929684],"iteration":47,"passed_time":0.08050751386,"remaining_time":0.08721647335},
{"learn":[5.108792602],"iteration":48,"passed_time":0.08264912848,"remaining_time":0.0860225623},
{"learn":[5.098141225],"iteration":49,"passed_time":0.08427910558,"remaining_time":0.08427910558},
{"learn":[5.085926393],"iteration":50,"passed_time":0.08642546843,"remaining_time":0.08303623438},
{"learn":[5.067816804],"iteration":51,"passed_time":0.08814205663,"remaining_time":0.08136189843},
{"learn":[5.049834901],"iteration":52,"passed_time":0.08983363014,"remaining_time":0.07966378522},
{"learn":[5.03838627],"iteration":53,"passed_time":0.09129099673,"remaining_time":0.07776640462},
{"learn":[5.033534248],"iteration":54,"passed_time":0.0923340119,"remaining_time":0.07554600974},
{"learn":[5.023726885],"iteration":55,"passed_time":0.09415119366,"remaining_time":0.07397593788},
{"learn":[5.01290392],"iteration":56,"passed_time":0.09601229883,"remaining_time":0.07243033069},
{"learn":[5.005569127],"iteration":57,"passed_time":0.09794803061,"remaining_time":0.07092788423},
{"learn":[4.989969032],"iteration":58,"passed_time":0.09967472307,"remaining_time":0.06926548552},
{"learn":[4.976762446],"iteration":59,"passed_time":0.1011790726,"remaining_time":0.06745271507},
{"learn":[4.967222715],"iteration":60,"passed_time":0.102818033,"remaining_time":0.06573611943},
{"learn":[4.954407599],"iteration":61,"passed_time":0.1045148548,"remaining_time":0.06405749163},
{"learn":[4.942125056],"iteration":62,"passed_time":0.1059814236,"remaining_time":0.06224305828},
{"learn":[4.930230716],"iteration":63,"passed_time":0.1075930669,"remaining_time":0.06052110015},
{"learn":[4.921695642],"iteration":64,"passed_time":0.1090586761,"remaining_time":0.05872390252},
{"learn":[4.906405625],"iteration":65,"passed_time":0.1108621283,"remaining_time":0.05711079338},
{"learn":[4.894330248],"iteration":66,"passed_time":0.1126361374,"remaining_time":0.0554775005},
{"learn":[4.88211557],"iteration":67,"passed_time":0.1143260716,"remaining_time":0.0538005043},
{"learn":[4.877946398],"iteration":68,"passed_time":0.1158415353,"remaining_time":0.05204474773},
{"learn":[4.863182126],"iteration":69,"passed_time":0.117286386,"remaining_time":0.050265594},
{"learn":[4.84646533],"iteration":70,"passed_time":0.1186826624,"remaining_time":0.04847601706},
{"learn":[4.838014752],"iteration":71,"passed_time":0.1204719295,"remaining_time":0.04685019479},
{"learn":[4.82981137],"iteration":72,"passed_time":0.1222186521,"remaining_time":0.04520415898},
{"learn":[4.817094767],"iteration":73,"passed_time":0.1237298834,"remaining_time":0.04347266172},
{"learn":[4.808314151],"iteration":74,"passed_time":0.1253627153,"remaining_time":0.04178757178},
{"learn":[4.796235023],"iteration":75,"passed_time":0.1271212069,"remaining_time":0.04014353903},
{"learn":[4.784434534],"iteration":76,"passed_time":0.1287051796,"remaining_time":0.0384444043},
{"learn":[4.774402487],"iteration":77,"passed_time":0.1302663464,"remaining_time":0.03674179002},
{"learn":[4.76731896],"iteration":78,"passed_time":0.1319237498,"remaining_time":0.03506833855},
{"learn":[4.75934113],"iteration":79,"passed_time":0.1332819918,"remaining_time":0.03332049794},
{"learn":[4.754106378],"iteration":80,"passed_time":0.1348715476,"remaining_time":0.03163653585},
{"learn":[4.744002932],"iteration":81,"passed_time":0.1364398692,"remaining_time":0.02995021518},
{"learn":[4.731700554],"iteration":82,"passed_time":0.1382031839,"remaining_time":0.02830667622},
{"learn":[4.723284153],"iteration":83,"passed_time":0.140550542,"remaining_time":0.0267715318},
{"learn":[4.712232782],"iteration":84,"passed_time":0.1427595141,"remaining_time":0.02519285543},
{"learn":[4.703046867],"iteration":85,"passed_time":0.1448287195,"remaining_time":0.02357676828},
{"learn":[4.698601855],"iteration":86,"passed_time":0.1465927803,"remaining_time":0.02190466831},
{"learn":[4.692429407],"iteration":87,"passed_time":0.1492590958,"remaining_time":0.02035351307},
{"learn":[4.675027364],"iteration":88,"passed_time":0.1515654483,"remaining_time":0.01873280822},
{"learn":[4.662368584],"iteration":89,"passed_time":0.1533463086,"remaining_time":0.01703847873},
{"learn":[4.646206172],"iteration":90,"passed_time":0.1554030881,"remaining_time":0.01536953619},
{"learn":[4.641245848],"iteration":91,"passed_time":0.1577841251,"remaining_time":0.01372035871},
{"learn":[4.633900435],"iteration":92,"passed_time":0.1591475544,"remaining_time":0.01197884818},
{"learn":[4.624738236],"iteration":93,"passed_time":0.1606361918,"remaining_time":0.01025337395},
{"learn":[4.612798287],"iteration":94,"passed_time":0.1622233689,"remaining_time":0.008538072046},
{"learn":[4.605222001],"iteration":95,"passed_time":0.1637237703,"remaining_time":0.006821823763},
{"learn":[4.601725912],"iteration":96,"passed_time":0.1654105083,"remaining_time":0.005115788917},
{"learn":[4.59722371],"iteration":97,"passed_time":0.1669209905,"remaining_time":0.003406550826},
{"learn":[4.580235665],"iteration":98,"passed_time":0.1683053967,"remaining_time":0.001700054512},
{"learn":[4.57591791],"iteration":99,"passed_time":0.1700962906,"remaining_time":0}
]}